RESTArt_Falcon-0.1.0.dist-info/WHEEL
RESTArt_Falcon-0.1.0.dist-info/RECORD
RESTArt_Falcon-0.1.0.dist-info/METADATA
RESTArt_Falcon-0.1.0.dist-info/metadata.json
RESTArt_Falcon-0.1.0.dist-info/top_level.txt
RESTArt_Falcon-0.1.0.dist-info/DESCRIPTION.rst
restart_falcon/__init__.py
restart_falcon/request.py
restart_falcon/adapter.py
