Metadata-Version: 2.0
Name: RESTArt-Falcon
Version: 0.1.0
Summary: A RESTArt extension for integrating RESTArt into Falcon, which has the benefit of high performance.
Home-page: https://github.com/RussellLuo/restart-falcon
Author: RussellLuo
Author-email: luopeng.he@gmail.com
License: MIT
Keywords: REST APIs,RESTArt,Falcon,Python
Platform: UNKNOWN
Requires-Dist: python-restart
Requires-Dist: falcon
